llm_strings/__init__.py
llm_strings/source.py
llm_strings-0.1.3.dist-info/LICENSE
llm_strings-0.1.3.dist-info/METADATA
llm_strings-0.1.3.dist-info/WHEEL
llm_strings-0.1.3.dist-info/top_level.txt
llm_strings-0.1.3.dist-info/RECORD
