Metadata-Version: 2.1
Name: llm_strings
Version: 0.1.3
Summary: A brief description of my package
Author-email: Juan Wisznia <juanwisznia@gmail.com>
License: MIT License
License-File: LICENSE
